ctg_data_helpers/__init__.py
ctg_data_helpers/helper_functions.py
ctg_data_helpers-0.0.1.dist-info/LICENSE
ctg_data_helpers-0.0.1.dist-info/METADATA
ctg_data_helpers-0.0.1.dist-info/WHEEL
ctg_data_helpers-0.0.1.dist-info/top_level.txt
ctg_data_helpers-0.0.1.dist-info/RECORD
