Metadata-Version: 2.1
Name: ctg-data-helpers
Version: 0.0.1
Summary: A helpful module for downloading, processing and ingesting data
Home-page: https://github.com/capitaltg/ctg-data-helpers
Author: Capital Technology Group
Author-email: sengel@capitaltg.com
License: UNKNOWN
Project-URL: Bug Tracker, https://github.com/capitaltg/ctg-data-helpers/issues
Platform: UNKNOWN
Classifier: Programming Language :: Python :: 3
Classifier: License :: OSI Approved :: MIT License
Classifier: Operating System :: OS Independent
Requires-Python: >=3.6
License-File: LICENSE
Requires-Dist: pandas
Requires-Dist: psycopg2-binary
Requires-Dist: sqlalchemy
Requires-Dist: requests
